panchemy/__init__.py
panchemy/base.py
panchemy/handler.py
panchemy/log.py
panchemy/model.py
panchemy-0.0.8.dist-info/LICENSE
panchemy-0.0.8.dist-info/WHEEL
panchemy-0.0.8.dist-info/METADATA
panchemy-0.0.8.dist-info/RECORD
